nspec/__init__.py
nspec/__main__.py
nspec/checkers.py
nspec/cli.py
nspec/cli_commands.py
nspec/config.py
nspec/crud.py
nspec/datasets.py
nspec/dev_metrics.py
nspec/ids.py
nspec/init.py
nspec/mcp_server.py
nspec/migrate_adrs.py
nspec/operations.py
nspec/paths.py
nspec/reports.py
nspec/session.py
nspec/skills/__init__.py
nspec/skills/backlog-handoff.md
nspec/skills/backlog.md
nspec/skills/go.md
nspec/skills/loop.md
nspec/skills/verify-tests.md
nspec/spinner.py
nspec/statuses.py
nspec/summary.py
nspec/table_formatter.py
nspec/tasks.py
nspec/templates/__init__.py
nspec/templates/init/__init__.py
nspec/templates/init/ci_cloudbuild.py
nspec/templates/init/ci_github.py
nspec/templates/init/ci_gitlab.py
nspec/templates/init/nspec_mk.py
nspec/templates/reports/base.j2
nspec/templates/reports/report_screen.tcss
nspec/templates/reports/section_blockers.j2
nspec/templates/reports/section_list.j2
nspec/templates/reports/section_matrix.j2
nspec/templates/reports/section_metrics.j2
nspec/templates/reports/section_table.j2
nspec/tui/__init__.py
nspec/tui/app.py
nspec/tui/detail_screen.py
nspec/tui/nspec.tcss
nspec/tui/report_screen.py
nspec/tui/state.py
nspec/tui/table.py
nspec/tui/templates/reports/report_screen.tcss
nspec/tui/utils.py
nspec/tui/widgets.py
nspec/validator.py
nspec/validators.py
nspec/velocity.py
nspec-1.0.1.dist-info/METADATA
nspec-1.0.1.dist-info/WHEEL
nspec-1.0.1.dist-info/entry_points.txt
nspec-1.0.1.dist-info/licenses/LICENSE
nspec-1.0.1.dist-info/RECORD
