Metadata-Version: 2.4
Name: nspec
Version: 1.0.1
Summary: Feature request and implementation specification management tool
License: MIT
License-File: LICENSE
Keywords: requirements,specifications,project-management,validation,cli
Author: Novabuiltdevv
Requires-Python: >=3.11,<4.0
Classifier: Development Status :: 4 - Beta
Classifier: Environment :: Console
Classifier: Intended Audience :: Developers
Classifier: License :: OSI Approved :: MIT License
Classifier: Operating System :: OS Independent
Classifier: Programming Language :: Python :: 3
Classifier: Programming Language :: Python :: 3.11
Classifier: Programming Language :: Python :: 3.12
Classifier: Programming Language :: Python :: 3.13
Classifier: Programming Language :: Python :: 3.14
Classifier: Topic :: Software Development :: Documentation
Classifier: Topic :: Software Development :: Quality Assurance
Provides-Extra: completion
Provides-Extra: mcp
Requires-Dist: argcomplete (>=3.0,<4.0) ; extra == "completion"
Requires-Dist: mcp (>=1.0,<2.0) ; extra == "mcp"
Requires-Dist: textual (>=7.4,<8.0)
Project-URL: Documentation, https://github.com/Novabuiltdevv/nspec#readme
Project-URL: Homepage, https://github.com/Novabuiltdevv/nspec
Project-URL: Repository, https://github.com/Novabuiltdevv/nspec
